setup.py
django_sql_caching.egg-info/PKG-INFO
django_sql_caching.egg-info/SOURCES.txt
django_sql_caching.egg-info/dependency_links.txt
django_sql_caching.egg-info/not-zip-safe
django_sql_caching.egg-info/requires.txt
django_sql_caching.egg-info/top_level.txt
sql_caching/__init__.py
sql_caching/middleware.py