Metadata-Version: 1.0
Name: django-sql-caching
Version: 0.1.0
Summary: Cache DB reads on per-request basis.
Home-page: https://github.com/Rhumbix/django-sql-caching.git
Author: Kenneth Jiang
Author-email: kenneth@rhumbix.com
License: MIT
Platform: UNKNOWN
